solanaetl
tests
