Metadata-Version: 2.1
Name: solana-etl
Version: 0.0.2
Summary: Tools for exporting Solana blockchain data to CSV or JSON
Home-page: https://github.com/blockchain-etl/solana-etl
Author: Gamejam.com
Author-email: info@gamejam.com
License: UNKNOWN
Project-URL: Bug Reports, https://github.com/blockchain-etl/solana-etl/issues
Project-URL: Source, https://github.com/blockchain-etl/solana-etl
Keywords: solana
Platform: UNKNOWN
Classifier: Development Status :: 5 - Production/Stable
Classifier: Intended Audience :: Developers
Classifier: License :: OSI Approved :: MIT License
Classifier: Programming Language :: Python :: 3
Classifier: Programming Language :: Python :: 3.7
Classifier: Programming Language :: Python :: 3.8
Classifier: Programming Language :: Python :: 3.9
Requires-Python: >=3.6,<3.10
